pm4ngs/__init__.py
pm4ngs/cloud/__init__.py
pm4ngs/cloud/gcp.py
pm4ngs/cookiecutter.py
pm4ngs/jupyterngsplugin/__init__.py
pm4ngs/jupyterngsplugin/databases/__init__.py
pm4ngs/jupyterngsplugin/databases/sra.py
pm4ngs/jupyterngsplugin/files/__init__.py
pm4ngs/jupyterngsplugin/files/fastq/__init__.py
pm4ngs/jupyterngsplugin/files/fastq/fastqc.py
pm4ngs/jupyterngsplugin/image/__init__.py
pm4ngs/jupyterngsplugin/image/pdftobase64.py
pm4ngs/jupyterngsplugin/image/pngtobase64.py
pm4ngs/jupyterngsplugin/markdown/__init__.py
pm4ngs/jupyterngsplugin/markdown/alignment.py
pm4ngs/jupyterngsplugin/markdown/chipexo.py
pm4ngs/jupyterngsplugin/markdown/chipseq.py
pm4ngs/jupyterngsplugin/markdown/fastqc.py
pm4ngs/jupyterngsplugin/markdown/phantompeakqualtools.py
pm4ngs/jupyterngsplugin/markdown/rnaseq/__init__.py
pm4ngs/jupyterngsplugin/markdown/rnaseq/dga.py
pm4ngs/jupyterngsplugin/markdown/rnaseq/go.py
pm4ngs/jupyterngsplugin/markdown/rnaseq/quantification.py
pm4ngs/jupyterngsplugin/markdown/rseqc.py
pm4ngs/jupyterngsplugin/markdown/utils.py
pm4ngs/jupyterngsplugin/utils/__init__.py
pm4ngs/jupyterngsplugin/utils/count_lines.py
pm4ngs/jupyterngsplugin/utils/errors.py
pm4ngs/jupyterngsplugin/utils/load_content_dict.py
pm4ngs/jupyterngsplugin/utils/notebook.py
pm4ngs/jupyterngsplugin/utils/run_command.py
pm4ngs/jupyterngsplugin/utils/samples.py
pm4ngs/jupyterngsplugin/utils/working_dir.py
pm4ngs/jupyterngsplugin/utils/yaml_utils.py
pm4ngs/main.py
pm4ngs/taxonomy.py
pm4ngs/utils.py
pm4ngs-0.1.2.dist-info/METADATA
pm4ngs-0.1.2.dist-info/WHEEL
pm4ngs-0.1.2.dist-info/entry_points.txt
pm4ngs-0.1.2.dist-info/licenses/LICENSE
pm4ngs-0.1.2.dist-info/RECORD
