Metadata-Version: 2.4
Name: pm4ngs
Version: 0.1.2
Summary: PM4NGS generates a standard organizational structure for Next Generation Sequencing (ngs) data analysis
License: Public Domain
License-File: LICENSE
Keywords: Biocontainers,Bioinformatics,NGS,Genomics
Author: Vera Alvarez, Roberto
Author-email: veraalva@ncbi.nlm.nih.gov
Maintainer: Vera Alvarez, Roberto
Maintainer-email: veraalva@ncbi.nlm.nih.gov
Requires-Python: >=3.9,<4.0
Classifier: Development Status :: 3 - Alpha
Classifier: Intended Audience :: Science/Research
Classifier: License :: Other/Proprietary License
Classifier: License :: Public Domain
Classifier: Natural Language :: English
Classifier: Operating System :: Unix
Classifier: Programming Language :: Python :: 3
Classifier: Programming Language :: Python :: 3.9
Classifier: Programming Language :: Python :: 3.10
Classifier: Programming Language :: Python :: 3.11
Classifier: Programming Language :: Python :: 3.12
Classifier: Programming Language :: Python :: 3.13
Classifier: Programming Language :: Python :: 3.14
Classifier: Topic :: Scientific/Engineering :: Bio-Informatics
Requires-Dist: GitPython
Requires-Dist: PyYAML
Requires-Dist: bioconda2biocontainer
Requires-Dist: biopython
Requires-Dist: cookiecutter
Requires-Dist: cwltool
Requires-Dist: docker
Requires-Dist: goenrichment
Requires-Dist: jupyter
Requires-Dist: matplotlib
Requires-Dist: networkx
Requires-Dist: numpy
Requires-Dist: pandas
Requires-Dist: pdf2image
Requires-Dist: requests
Requires-Dist: scipy
Requires-Dist: seaborn
Requires-Dist: statsmodels
Requires-Dist: urllib3
Requires-Dist: xmltodict
Project-URL: Documentation, https://pm4ngs.readthedocs.io/
Project-URL: Homepage, https://github.com/ncbi/pm4ngs
Project-URL: Repository, https://github.com/ncbi/pm4ngs
Project-URL: Tracker, https://github.com/ncbi/pm4ngs/issues
